pyfoxtrot/AuthenticatedClient.py
pyfoxtrot/Client.py
pyfoxtrot/EnumCreator.py
pyfoxtrot/Errors.py
pyfoxtrot/Sessions.py
pyfoxtrot/TelemetryCatcher.py
pyfoxtrot/TypeConversion.py
pyfoxtrot/__init__.py
pyfoxtrot/common.py
pyfoxtrot/protos/foxtrot_pb2.py
pyfoxtrot/protos/foxtrot_pb2.pyi
pyfoxtrot/protos/foxtrot_pb2_grpc.py
pyfoxtrot/protos/foxtrot_pb2_grpc.pyi
pyfoxtrot/protos/ft_auth_pb2.py
pyfoxtrot/protos/ft_auth_pb2.pyi
pyfoxtrot/protos/ft_auth_pb2_grpc.py
pyfoxtrot/protos/ft_auth_pb2_grpc.pyi
pyfoxtrot/protos/ft_capability_pb2.py
pyfoxtrot/protos/ft_capability_pb2.pyi
pyfoxtrot/protos/ft_capability_pb2_grpc.py
pyfoxtrot/protos/ft_capability_pb2_grpc.pyi
pyfoxtrot/protos/ft_error_pb2.py
pyfoxtrot/protos/ft_error_pb2.pyi
pyfoxtrot/protos/ft_error_pb2_grpc.py
pyfoxtrot/protos/ft_error_pb2_grpc.pyi
pyfoxtrot/protos/ft_flags_pb2.py
pyfoxtrot/protos/ft_flags_pb2.pyi
pyfoxtrot/protos/ft_flags_pb2_grpc.py
pyfoxtrot/protos/ft_flags_pb2_grpc.pyi
pyfoxtrot/protos/ft_sessions_pb2.py
pyfoxtrot/protos/ft_sessions_pb2.pyi
pyfoxtrot/protos/ft_sessions_pb2_grpc.py
pyfoxtrot/protos/ft_sessions_pb2_grpc.pyi
pyfoxtrot/protos/ft_streams_pb2.py
pyfoxtrot/protos/ft_streams_pb2.pyi
pyfoxtrot/protos/ft_streams_pb2_grpc.py
pyfoxtrot/protos/ft_streams_pb2_grpc.pyi
pyfoxtrot/protos/ft_types_pb2.py
pyfoxtrot/protos/ft_types_pb2.pyi
pyfoxtrot/protos/ft_types_pb2_grpc.py
pyfoxtrot/protos/ft_types_pb2_grpc.pyi
pyfoxtrot/server_flags.py
foxtrotpy-0.1.1.dist-info/WHEEL
foxtrotpy-0.1.1.dist-info/METADATA
foxtrotpy-0.1.1.dist-info/RECORD
