Metadata-Version: 2.1
Name: foxtrotpy
Version: 0.1.1
Summary: Client for Foxtrot RPC hardware server
Author: Dan Weatherill
Author-email: daniel.weatherill@physics.ox.ac.uk
Requires-Python: >=3.8,<4.0
Classifier: Programming Language :: Python :: 3
Classifier: Programming Language :: Python :: 3.8
Classifier: Programming Language :: Python :: 3.9
Classifier: Programming Language :: Python :: 3.10
Requires-Dist: poetry-grpc-plugin (>=0.1.2,<0.2.0)
Requires-Dist: protobuf (<=3.20)
